{"release_time": "2024-10-19 10:14:10", "update_time": "2024-10-19 10:14:13", "description": {"title": "豆瓣最受欢迎的影评", "subtitle": "豆瓣最受欢迎的影评", "source": "https://www.douban.com", "link": "https://movie.douban.com/review/movie_best/", "page_start": 1, "page_end": 1, "page_total": 1, "page_limit": -1, "item_total": 1, "item_limit": 1, "page_count": 1, "sup_page_count": 0, "my-query-id": "review-movie"}, "extra": {"description": "豆瓣成员投票选出的最佳影评", "language": "zh-cn", "copyright": "&copy; 2013, douban.com.", "pubDate": "Fri, 18 Oct 2024 22:19:16 GMT"}, "stats": {"movies": 20}, "movies": [{"title": "《某种物质》: 焦虑自反与身体议题 (评论: 某种物质)", "link": "https://movie.douban.com/review/16247021/", "description": "九苍评论: 某种物质 (http://movie.douban.com/subject/35882838/)\n评价: \n\n{\"blocks\":[{\"key\":\"7sfj3\",\"text\":\"\",\"type\":\"unstyled\",\"depth\":0,\"inlineStyleRanges\":[],\"entityRanges\":[],\"data\":{}},{\"key\":\"9s1i4\",\"text\":\"\",...", "content:encoded": "<img src=\"https://img1.doubanio.com/view/photo/s_ratio_poster/public/p2912441039.jpg\" style=\"float:right;margin-left:16px\"/><a\n    href=\"https://www.douban.com/people/neufly/\">九苍</a>评论: <a href=\"https://movie.douban.com/subject/35882838//\">某种物质</a><br/>\n<br/>评价: <br/><br/>", "dc:creator": "九苍", "pubDate": "Fri, 18 Oct 2024 22:19:16 GMT", "guid": {"@isPermaLink": "true", "#text": "https://movie.douban.com/review/16247021/"}}, {"title": "Sing if you like, dear. (评论: 育婴奇谭)", "link": "https://movie.douban.com/review/16246963/", "description": "TouMing柜子评论: 育婴奇谭 (http://movie.douban.com/subject/1297657/)\n评价: 力荐\n\n{\"blocks\":[{\"key\":\"4svfi\",\"text\":\"尽管，霍克斯自开场便借Susan之口提醒了我们：It's only a game, anyway。然而，从高尔夫球场的戏开始，整部电影就像Susan毫不理会David的抓狂一般...", "content:encoded": "<img src=\"https://img9.doubanio.com/view/photo/s_ratio_poster/public/p449637464.jpg\" style=\"float:right;margin-left:16px\"/><a\n    href=\"https://www.douban.com/people/Ophelia1022/\">TouMing柜子</a>评论: <a href=\"https://movie.douban.com/subject/1297657//\">育婴奇谭</a><br/>\n<br/>评价: 力荐<br/><br/>", "dc:creator": "TouMing柜子", "pubDate": "Fri, 18 Oct 2024 17:43:57 GMT", "guid": {"@isPermaLink": "true", "#text": "https://movie.douban.com/review/16246963/"}}, {"title": "当年被吐槽的浪姐五公 是黄圣依的觉醒时刻 (评论: 再见爱人 第四季)", "link": "https://movie.douban.com/review/16245204/", "description": "Lalalaland评论: 再见爱人 第四季 (http://movie.douban.com/subject/36642447/)\n评价: 推荐\n\n{\"entityMap\": {\"0\": {\"type\": \"IMAGE\", \"data\": {\"origin\": false, \"src\": \"...", "content:encoded": "<img src=\"https://img1.doubanio.com/view/photo/s_ratio_poster/public/p2914330680.jpg\" style=\"float:right;margin-left:16px\"/><a\n    href=\"https://www.douban.com/people/152828679/\">Lalalaland</a>评论: <a href=\"https://movie.douban.com/subject/36642447//\">再见爱人 第四季</a><br/>\n<br/>评价: 推荐<br/><br/>", "dc:creator": "Lalalaland", "pubDate": "Thu, 17 Oct 2024 15:48:21 GMT", "guid": {"@isPermaLink": "true", "#text": "https://movie.douban.com/review/16245204/"}}, {"title": "【某种物质】导演：每一个看秀的观众，都是凶手 (评论: 某种物质)", "link": "https://movie.douban.com/review/16239642/", "description": "女神的秋裤评论: 某种物质 (http://movie.douban.com/subject/35882838/)\n评价: 推荐\n\n{\"blocks\":[{\"key\":\"f66n1\",\"text\":\"欢迎关注公众号“影探”\",\"type\":\"unstyled\",\"depth\":0,\"inlineS...", "content:encoded": "<img src=\"https://img1.doubanio.com/view/photo/s_ratio_poster/public/p2912441039.jpg\" style=\"float:right;margin-left:16px\"/><a\n    href=\"https://www.douban.com/people/movieater/\">女神的秋裤</a>评论: <a href=\"https://movie.douban.com/subject/35882838//\">某种物质</a><br/>\n<br/>评价: 推荐<br/><br/>", "dc:creator": "女神的秋裤", "pubDate": "Mon, 14 Oct 2024 10:12:09 GMT", "guid": {"@isPermaLink": "true", "#text": "https://movie.douban.com/review/16239642/"}}, {"title": "井胧是有什么搞笑体质嘛 (评论: 披荆斩棘 第四季)", "link": "https://movie.douban.com/review/16247304/", "description": "lldjw评论: 披荆斩棘 第四季 (http://movie.douban.com/subject/36643635/)\n评价: 力荐\n\n{\"entityMap\": {\"0\": {\"data\": {\"origin\": false, \"src\": \"https://img9.doub...", "content:encoded": "<img src=\"https://img3.doubanio.com/view/photo/s_ratio_poster/public/p2911343702.jpg\" style=\"float:right;margin-left:16px\"/><a\n    href=\"https://www.douban.com/people/lldjwCJS/\">lldjw</a>评论: <a href=\"https://movie.douban.com/subject/36643635//\">披荆斩棘 第四季</a><br/>\n<br/>评价: 力荐<br/><br/>", "dc:creator": "lldjw", "pubDate": "Sat, 19 Oct 2024 04:03:34 GMT", "guid": {"@isPermaLink": "true", "#text": "https://movie.douban.com/review/16247304/"}}, {"title": "【自译中字】曼努埃尔·德·法雅的音乐人生 (评论: Life and Death of Manuel de Falla)", "link": "https://movie.douban.com/review/16243529/", "description": "月酊评论: Life and Death of Manuel de Falla (http://movie.douban.com/subject/5094043/)\n评价: \n\n{\"blocks\":[{\"key\":\"4rlfi\",\"text\":\"b站源：BV1R8mMY3EwG\",\"type\":\"unstyled\",\"depth\":0,\"in...", "content:encoded": "<img src=\"https://img3.doubanio.com/view/photo/s_ratio_poster/public/p2512185962.jpg\" style=\"float:right;margin-left:16px\"/><a\n    href=\"https://www.douban.com/people/279304701/\">月酊</a>评论: <a href=\"https://movie.douban.com/subject/5094043//\">Life and Death of Manuel de Falla</a><br/>\n<br/>评价: <br/><br/>", "dc:creator": "月酊", "pubDate": "Wed, 16 Oct 2024 14:39:51 GMT", "guid": {"@isPermaLink": "true", "#text": "https://movie.douban.com/review/16243529/"}}, {"title": "欲望的残羹——人物心理与镜头分析 (评论: 某种物质)", "link": "https://movie.douban.com/review/16241486/", "description": "图克评论: 某种物质 (http://movie.douban.com/subject/35882838/)\n评价: 推荐\n\n{\"entityMap\": {\"0\": {\"type\": \"IMAGE\", \"data\": {\"origin\": false, \"src\": \"...", "content:encoded": "<img src=\"https://img1.doubanio.com/view/photo/s_ratio_poster/public/p2912441039.jpg\" style=\"float:right;margin-left:16px\"/><a\n    href=\"https://www.douban.com/people/MZQ1023/\">图克</a>评论: <a href=\"https://movie.douban.com/subject/35882838//\">某种物质</a><br/>\n<br/>评价: 推荐<br/><br/>", "dc:creator": "图克", "pubDate": "Tue, 15 Oct 2024 10:41:15 GMT", "guid": {"@isPermaLink": "true", "#text": "https://movie.douban.com/review/16241486/"}}, {"title": "沦为小丑的，到底是哪个小丑 (评论: 小丑2：双重妄想)", "link": "https://movie.douban.com/review/16246653/", "description": "人间烟火评论: 小丑2：双重妄想 (http://movie.douban.com/subject/34909341/)\n评价: 力荐\n\n{\"entityMap\": {\"0\": {\"data\": {\"origin\": false, \"src\": \"https://img3.doub...", "content:encoded": "<img src=\"https://img1.doubanio.com/view/photo/s_ratio_poster/public/p2913969438.jpg\" style=\"float:right;margin-left:16px\"/><a\n    href=\"https://www.douban.com/people/hyb520520520/\">人间烟火</a>评论: <a href=\"https://movie.douban.com/subject/34909341//\">小丑2：双重妄想</a><br/>\n<br/>评价: 力荐<br/><br/>", "dc:creator": "人间烟火", "pubDate": "Fri, 18 Oct 2024 14:13:21 GMT", "guid": {"@isPermaLink": "true", "#text": "https://movie.douban.com/review/16246653/"}}, {"title": "哥谭需要一个小丑 (评论: 小丑2：双重妄想)", "link": "https://movie.douban.com/review/16243231/", "description": "方聿南评论: 小丑2：双重妄想 (http://movie.douban.com/subject/34909341/)\n评价: 较差\n\n{\"blocks\":[{\"key\":\"d6m2b\",\"text\":\"我们一度以为亚瑟·弗莱彻就是那个哥谭的常驻恶棍。\",\"type\":\"unstyled\",\"depth\":0,\"inl...", "content:encoded": "<img src=\"https://img1.doubanio.com/view/photo/s_ratio_poster/public/p2913969438.jpg\" style=\"float:right;margin-left:16px\"/><a\n    href=\"https://www.douban.com/people/fangyunan/\">方聿南</a>评论: <a href=\"https://movie.douban.com/subject/34909341//\">小丑2：双重妄想</a><br/>\n<br/>评价: 较差<br/><br/>", "dc:creator": "方聿南", "pubDate": "Wed, 16 Oct 2024 12:03:28 GMT", "guid": {"@isPermaLink": "true", "#text": "https://movie.douban.com/review/16243231/"}}, {"title": "对权力、阶级及女性处境的一点思考 (评论: 思想验证区域：The Community)", "link": "https://movie.douban.com/review/16246674/", "description": "airy评论: 思想验证区域：The Community (http://movie.douban.com/subject/36722428/)\n评价: 力荐\n\n{\"blocks\":[{\"key\":\"bbetd\",\"text\":\"这是今年我最喜欢的综艺，像是真实社会的超级缩小版，里面涉及生存竞争、政治选举、合作生产、社交联盟，并且展现了对社会议题的讨论和观念的碰撞。这也引发了我的很多思考，尤其对权力、阶级、女性处境以及人的复杂性有了更深入的思考...", "content:encoded": "<img src=\"https://img1.doubanio.com/view/photo/s_ratio_poster/public/p2903848858.jpg\" style=\"float:right;margin-left:16px\"/><a\n    href=\"https://www.douban.com/people/airy5/\">airy</a>评论: <a href=\"https://movie.douban.com/subject/36722428//\">思想验证区域：The Community</a><br/>\n<br/>评价: 力荐<br/><br/>", "dc:creator": "airy", "pubDate": "Fri, 18 Oct 2024 14:23:00 GMT", "guid": {"@isPermaLink": "true", "#text": "https://movie.douban.com/review/16246674/"}}, {"title": "【译】《利维坦》与感官民族志中的体验 (评论: 利维坦)", "link": "https://movie.douban.com/review/16245293/", "description": "世界的焚像.评论: 利维坦 (http://movie.douban.com/subject/11500300/)\n评价: 推荐\n\n{\"entityMap\": {\"0\": {\"type\": \"SEPARATOR\", \"data\": {}, \"mutability\": \"IMM...", "content:encoded": "<img src=\"https://img9.doubanio.com/view/photo/s_ratio_poster/public/p1857954526.jpg\" style=\"float:right;margin-left:16px\"/><a\n    href=\"https://www.douban.com/people/Fengeral0808/\">世界的焚像.</a>评论: <a href=\"https://movie.douban.com/subject/11500300//\">利维坦</a><br/>\n<br/>评价: 推荐<br/><br/>", "dc:creator": "世界的焚像.", "pubDate": "Thu, 17 Oct 2024 17:05:43 GMT", "guid": {"@isPermaLink": "true", "#text": "https://movie.douban.com/review/16245293/"}}, {"title": "破地獄 (评论: 破·地狱)", "link": "https://movie.douban.com/review/16245119/", "description": "Avocado评论: 破·地狱 (http://movie.douban.com/subject/36712987/)\n评价: 力荐\n\n{\"entityMap\": {}, \"blocks\": [{\"text\": \"5\", \"entityRanges\": [], \"depth\": ...", "content:encoded": "<img src=\"https://img2.doubanio.com/view/photo/s_ratio_poster/public/p2909631191.jpg\" style=\"float:right;margin-left:16px\"/><a\n    href=\"https://www.douban.com/people/277684140/\">Avocado</a>评论: <a href=\"https://movie.douban.com/subject/36712987//\">破·地狱</a><br/>\n<br/>评价: 力荐<br/><br/>", "dc:creator": "Avocado", "pubDate": "Thu, 17 Oct 2024 14:54:43 GMT", "guid": {"@isPermaLink": "true", "#text": "https://movie.douban.com/review/16245119/"}}, {"title": "看《时光音乐会》被李斯丹妮圈粉了！ (评论: 时光音乐会 第四季)", "link": "https://movie.douban.com/review/16246354/", "description": "唱唱反调_评论: 时光音乐会 第四季 (http://movie.douban.com/subject/37018273/)\n评价: 力荐\n\n{\"blocks\":[{\"key\":\"f2g9a\",\"text\":\"从来没有人告诉过我，李斯丹妮是这样一个宝藏女孩！以前从来没了解过，最近看《时光音乐会》第四季，真的...", "content:encoded": "<img src=\"https://img3.doubanio.com/view/photo/s_ratio_poster/public/p2914273373.jpg\" style=\"float:right;margin-left:16px\"/><a\n    href=\"https://www.douban.com/people/279583505/\">唱唱反调_</a>评论: <a href=\"https://movie.douban.com/subject/37018273//\">时光音乐会 第四季</a><br/>\n<br/>评价: 力荐<br/><br/>", "dc:creator": "唱唱反调_", "pubDate": "Fri, 18 Oct 2024 11:09:00 GMT", "guid": {"@isPermaLink": "true", "#text": "https://movie.douban.com/review/16246354/"}}, {"title": "逃出密室，除蛇扬善 (评论: 哈利·波特与密室)", "link": "https://movie.douban.com/review/16247281/", "description": "落木Lin评论: 哈利·波特与密室 (http://movie.douban.com/subject/1296996/)\n评价: 力荐\n\n{\"entityMap\": {\"0\": {\"data\": {\"url\": \"https://movie.douban.com/subject/1...", "content:encoded": "<img src=\"https://img2.doubanio.com/view/photo/s_ratio_poster/public/p2913781951.jpg\" style=\"float:right;margin-left:16px\"/><a\n    href=\"https://www.douban.com/people/lllllwt1222228/\">落木Lin</a>评论: <a href=\"https://movie.douban.com/subject/1296996//\">哈利·波特与密室</a><br/>\n<br/>评价: 力荐<br/><br/>", "dc:creator": "落木Lin", "pubDate": "Sat, 19 Oct 2024 03:44:06 GMT", "guid": {"@isPermaLink": "true", "#text": "https://movie.douban.com/review/16247281/"}}, {"title": "当小丑不再疯狂 (评论: 小丑2：双重妄想)", "link": "https://movie.douban.com/review/16244676/", "description": "混沌不开窍评论: 小丑2：双重妄想 (http://movie.douban.com/subject/34909341/)\n评价: 力荐\n\n{\"blocks\":[{\"key\":\"9e0gn\",\"text\":\"《小丑》曾是一部引发我痛觉的电影。\",\"type\":\"unstyled\",\"depth\":0,\"inlineStyleRan...", "content:encoded": "<img src=\"https://img1.doubanio.com/view/photo/s_ratio_poster/public/p2913969438.jpg\" style=\"float:right;margin-left:16px\"/><a\n    href=\"https://www.douban.com/people/161899295/\">混沌不开窍</a>评论: <a href=\"https://movie.douban.com/subject/34909341//\">小丑2：双重妄想</a><br/>\n<br/>评价: 力荐<br/><br/>", "dc:creator": "混沌不开窍", "pubDate": "Thu, 17 Oct 2024 10:01:54 GMT", "guid": {"@isPermaLink": "true", "#text": "https://movie.douban.com/review/16244676/"}}, {"title": "二流动作设计 不入流的剧情 (评论: 叛影浪客)", "link": "https://movie.douban.com/review/16246432/", "description": "纯蠢欲懂评论: 叛影浪客 (http://movie.douban.com/subject/36346792/)\n评价: \n\n{\"entityMap\": {}, \"blocks\": [{\"text\": \"\\u81ea\\u4ece\\u7a81\\u88ad\\u4ee5\\u5...", "content:encoded": "<img src=\"https://img9.doubanio.com/view/photo/s_ratio_poster/public/p2911862285.jpg\" style=\"float:right;margin-left:16px\"/><a\n    href=\"https://www.douban.com/people/192760100/\">纯蠢欲懂</a>评论: <a href=\"https://movie.douban.com/subject/36346792//\">叛影浪客</a><br/>\n<br/>评价: <br/><br/>", "dc:creator": "纯蠢欲懂", "pubDate": "Fri, 18 Oct 2024 12:20:54 GMT", "guid": {"@isPermaLink": "true", "#text": "https://movie.douban.com/review/16246432/"}}, {"title": "太阳部落是不是跟庆怜杠上了！ (评论: 披荆斩棘 第四季)", "link": "https://movie.douban.com/review/16244852/", "description": "唱唱反调_评论: 披荆斩棘 第四季 (http://movie.douban.com/subject/36643635/)\n评价: 力荐\n\n{\"blocks\":[{\"key\":\"cmekg\",\"text\":\"前方来报，太阳部落又梅开二度模仿庆怜啦！小可爱庆怜看到这里疑似失去了所有的力气和手段……\",\"type\":\"unstyled\"...", "content:encoded": "<img src=\"https://img3.doubanio.com/view/photo/s_ratio_poster/public/p2911343702.jpg\" style=\"float:right;margin-left:16px\"/><a\n    href=\"https://www.douban.com/people/279583505/\">唱唱反调_</a>评论: <a href=\"https://movie.douban.com/subject/36643635//\">披荆斩棘 第四季</a><br/>\n<br/>评价: 力荐<br/><br/>", "dc:creator": "唱唱反调_", "pubDate": "Thu, 17 Oct 2024 12:14:54 GMT", "guid": {"@isPermaLink": "true", "#text": "https://movie.douban.com/review/16244852/"}}, {"title": "其实导演只想拍成人片 (评论: 艾瑞斯)", "link": "https://movie.douban.com/review/16247604/", "description": "慧眼识天下评论: 艾瑞斯 (http://movie.douban.com/subject/26837803/)\n评价: 较差\n\n{\"blocks\":[{\"key\":\"cuqaf\",\"text\":\"导演讲的故事是这样的（剧不剧透无所谓了，这种片片你肯定会看了）：一个银行家有SM癖好，老婆满足不了就去找小姐，很自然不是，但是他又提了很多非同寻常的要求，比如让小姐跟踪老婆，模仿老婆的一言一行，那么按常理这个老公肯定有阴谋，然而并没有，他只是单纯的把SM小姐想象成老婆（这...", "content:encoded": "<img src=\"https://img1.doubanio.com/view/photo/s_ratio_poster/public/p2395369520.jpg\" style=\"float:right;margin-left:16px\"/><a\n    href=\"https://www.douban.com/people/193357205/\">慧眼识天下</a>评论: <a href=\"https://movie.douban.com/subject/26837803//\">艾瑞斯</a><br/>\n<br/>评价: 较差<br/><br/>", "dc:creator": "慧眼识天下", "pubDate": "Sat, 19 Oct 2024 07:56:22 GMT", "guid": {"@isPermaLink": "true", "#text": "https://movie.douban.com/review/16247604/"}}, {"title": "记录一下给我留下印象的主厨 (评论: 黑白厨师：料理阶级战争)", "link": "https://movie.douban.com/review/16244433/", "description": "樱花院评论: 黑白厨师：料理阶级战争 (http://movie.douban.com/subject/36598424/)\n评价: 推荐\n\n{\"blocks\":[{\"key\":\"3ni5p\",\"text\":\"爱德华李：用黑白来形容他都有点无力，已跳出黑白之外的大师。锐意创新，灵活机变，已臻化境。可以用“先锋派”来形容的主厨。他对食材的理解丰富、开放且深邃，有着艺术创作般的想象力，同时能够对每道菜进行近乎诗性的理念表达。团队赛迅速发现扇贝...", "content:encoded": "<img src=\"https://img1.doubanio.com/view/photo/s_ratio_poster/public/p2912027568.jpg\" style=\"float:right;margin-left:16px\"/><a\n    href=\"https://www.douban.com/people/160871617/\">樱花院</a>评论: <a href=\"https://movie.douban.com/subject/36598424//\">黑白厨师：料理阶级战争</a><br/>\n<br/>评价: 推荐<br/><br/>", "dc:creator": "樱花院", "pubDate": "Thu, 17 Oct 2024 07:16:30 GMT", "guid": {"@isPermaLink": "true", "#text": "https://movie.douban.com/review/16244433/"}}, {"title": "糟糕透顶的所谓前传 (评论: 7A公寓)", "link": "https://movie.douban.com/review/16247469/", "description": "SIM本体评论: 7A公寓 (http://movie.douban.com/subject/35412144/)\n评价: 较差\n\n{\"entityMap\": {\"0\": {\"data\": {\"origin\": false, \"src\": \"https://img3.doub...", "content:encoded": "<img src=\"https://img2.doubanio.com/view/photo/s_ratio_poster/public/p2911864391.jpg\" style=\"float:right;margin-left:16px\"/><a\n    href=\"https://www.douban.com/people/SIMself/\">SIM本体</a>评论: <a href=\"https://movie.douban.com/subject/35412144//\">7A公寓</a><br/>\n<br/>评价: 较差<br/><br/>", "dc:creator": "SIM本体", "pubDate": "Sat, 19 Oct 2024 06:32:00 GMT", "guid": {"@isPermaLink": "true", "#text": "https://movie.douban.com/review/16247469/"}}]}